{"run_number": "1626665497627618", "step_name": "end", "task_id": "2", "attempt_id": 0, "name": "name", "content_type": "gzip+pickle-v2", "type": "metaflow.artifact", "sha": "74b1eb166edc133e04f9d69b1c5d0a5957deee6d", "ds_type": "local", "location": "/Users/hamelsmu/github/learn-metaflow/.metaflow/ParameterFlow/data/74/74b1eb166edc133e04f9d69b1c5d0a5957deee6d", "flow_id": "ParameterFlow", "user_name": "hamelsmu", "tags": [], "system_tags": ["user:hamelsmu", "runtime:dev", "python_version:3.8.3", "date:2021-07-19", "metaflow_version:2.3.2"], "ts_epoch": 1626665499128}